LICENSE
MANIFEST.in
README.rst
requirements.txt
setup.cfg
setup.py
sma-template.ini
tox.ini
alerts/file.py
alerts/mail.py
alerts/telegram.py
monitors/example-1.sh
monitors/example-3.sh
monitors/google-cloud-print.py
monitors/hdds.sh
monitors/hddtemp.sh
monitors/mdadm.sh
monitors/ping.sh
monitors/sensors.py
monitors/service.sh
monitors/smart.sh
monitors/system.sh
monitors/web.py
scripts/sma
services/sma.service
services/sma.sh
simple_monitor_alert/__init__.py
simple_monitor_alert/alerts.py
simple_monitor_alert/exceptions.py
simple_monitor_alert/lines.py
simple_monitor_alert/management.py
simple_monitor_alert/monitor.py
simple_monitor_alert/sma.py
simple_monitor_alert.egg-info/PKG-INFO
simple_monitor_alert.egg-info/SOURCES.txt
simple_monitor_alert.egg-info/dependency_links.txt
simple_monitor_alert.egg-info/not-zip-safe
simple_monitor_alert.egg-info/pbr.json
simple_monitor_alert.egg-info/requires.txt
simple_monitor_alert.egg-info/top_level.txt
simple_monitor_alert/tests/__init__.py
simple_monitor_alert/tests/base.py
simple_monitor_alert/tests/test_alert.py
simple_monitor_alert/tests/test_ini.py
simple_monitor_alert/tests/test_monitor.py
simple_monitor_alert/tests/test_monitors.py
simple_monitor_alert/tests/test_observable.py
simple_monitor_alert/tests/test_results.py
simple_monitor_alert/tests/test_sma.py
simple_monitor_alert/tests/assets/sma-test.ini
simple_monitor_alert/tests/assets/monitors/ok-monitor.py
simple_monitor_alert/tests/assets/monitors/run-every.py
simple_monitor_alert/utils/__init__.py
simple_monitor_alert/utils/console.py
simple_monitor_alert/utils/dates.py
simple_monitor_alert/utils/files.py
simple_monitor_alert/utils/system.py