Metadata-Version: 1.1
Name: simple-monitor-alert
Version: 0.2.4
Summary: A simple monitor with alerts for Unix/Linux under the KISS philosophy. Keep It Simple, Stupid!
